{
  "videoId": "-tMTnGF5emE",
  "title": "Ronaldo Bigger Than The Saudi Pro League? | The Set Piece",
  "titleOverride": null,
  "slug": "ronaldo-bigger-than-the-saudi-pro-league-the-set-piece",
  "clubs": [],
  "venue": null,
  "competition": null,
  "format": "podcast",
  "story": "SAMPLE: Editorial line pending. Replace before publish.",
  "date": "2026-05-05",
  "duration": "PT1M47S",
  "featured": false,
  "embed": false,
  "needs_review": false,
  "review_reason": null,
  "playlists": [
    {
      "id": "PLl2YfuOasKzYAmJ5_RdrW6-LC4yihwg6r",
      "title": "The Set Piece | Episode 1 — Full Session"
    }
  ]
}
