{
  "videoId": "IC_Z__-Zkw4",
  "title": "Why Watching Your Own Country Play Feels Different",
  "titleOverride": null,
  "slug": "why-watching-your-own-country-play-feels-different",
  "clubs": [],
  "venue": null,
  "competition": null,
  "format": "explainer",
  "story": "SAMPLE: Editorial line pending. Replace before publish.",
  "date": "2026-07-01",
  "duration": "PT8M8S",
  "featured": false,
  "embed": false,
  "needs_review": false,
  "review_reason": null,
  "playlists": [
    {
      "id": "PLLEo9DMAhWvo",
      "title": "Norway in Dubai | World Cup 2026 Fan Documentary"
    }
  ]
}
